umnet_cyberark/__init__.py
umnet_cyberark-0.1.1.dist-info/LICENSE
umnet_cyberark-0.1.1.dist-info/METADATA
umnet_cyberark-0.1.1.dist-info/WHEEL
umnet_cyberark-0.1.1.dist-info/RECORD
