Metadata-Version: 2.3
Name: umnet-cyberark
Version: 0.1.1
Summary: Python package for querying Cyberark
Author: Amy Liebowitz
Author-email: amylieb@umich.edu
Requires-Python: >=3.6
Classifier: Programming Language :: Python :: 3
Classifier: Programming Language :: Python :: 3.6
Classifier: Programming Language :: Python :: 3.7
Classifier: Programming Language :: Python :: 3.8
Classifier: Programming Language :: Python :: 3.9
Classifier: Programming Language :: Python :: 3.10
Classifier: Programming Language :: Python :: 3.11
Classifier: Programming Language :: Python :: 3.12
Classifier: Programming Language :: Python :: 3.13
Requires-Dist: python-decouple (>=3.8,<4.0)
Requires-Dist: requests (>=2.32.3,<3.0.0)
